exp_datalab-0.1.0.dist-info/licenses/LICENSE
exp_tools/__init__.py
exp_tools/error_propagation.py
exp_tools/latex_report.py
exp_datalab-0.1.0.dist-info/METADATA
exp_datalab-0.1.0.dist-info/WHEEL
exp_datalab-0.1.0.dist-info/top_level.txt
exp_datalab-0.1.0.dist-info/RECORD
