Metadata-Version: 2.4
Name: exp-datalab
Version: 0.1.0
Summary: Experimental tools for scientific calculations, including error propagation and data analysis.
Author: Pablo Castro Pérez
License: MIT
Project-URL: Homepage, https://github.com/yourusername/exp_datalab
Project-URL: Bug Tracker, https://github.com/yourusername/exp_datalab/issues
Requires-Python: >=3.8
License-File: LICENSE
Requires-Dist: numpy>=1.22
Dynamic: license-file
